{
    "person1": {
        "voornaam": "Cagri",
        "familienaam": "Avci",
        "email": "cagravci@student.arteveldehs.be",
        "thumbnail": "https://external-content.duckduckgo.com/iu/?u=https%3A%2F%2Ftse1.mm.bing.net%2Fth%3Fid%3DOIP.ixpmln2hqkGMPpnBRYRQRAHaE9%26pid%3DApi&f=1",
        "lijfspreuk": "mijn lijfspreuk is mijn lijfgeur",
        "portfolio": {
            "GitHub gebruikersnaam": "drdynscript",
            "LinkedIn gebruikersnaam": "linked-cagravci"
        },
        "isStudentboolean": true,
        "geboortedatum":731363400000
    },
    "person2": {
        "voornaam": "Cagri",
        "familienaam": "Avci",
        "email": "cagravci@student.arteveldehs.be",
        "thumbnail": "https://external-content.duckduckgo.com/iu/?u=https%3A%2F%2Ftse1.mm.bing.net%2Fth%3Fid%3DOIP.ixpmln2hqkGMPpnBRYRQRAHaE9%26pid%3DApi&f=1",
        "lijfspreuk": "mijn lijfspreuk is mijn lijfgeur",
        "portfolio": {
            "GitHub gebruikersnaam": "drdynscript",
            "LinkedIn gebruikersnaam": "linked-cagravci"
        },
        "isStudentboolean": true,
        "geboortedatum":731363400000
    },
    "person3": {
        "voornaam": "Cagri",
        "familienaam": "Avci",
        "email": "cagravci@student.arteveldehs.be",
        "thumbnail": "https://external-content.duckduckgo.com/iu/?u=https%3A%2F%2Ftse1.mm.bing.net%2Fth%3Fid%3DOIP.ixpmln2hqkGMPpnBRYRQRAHaE9%26pid%3DApi&f=1",
        "lijfspreuk": "mijn lijfspreuk is mijn lijfgeur",
        "portfolio": {
            "GitHub gebruikersnaam": "drdynscript",
            "LinkedIn gebruikersnaam": "linked-cagravci"
        },
        "isStudentboolean": true,
        "geboortedatum":731363400000
    },
    "person4": {
        "voornaam": "Cagri",
        "familienaam": "Avci",
        "email": "cagravci@student.arteveldehs.be",
        "thumbnail": "https://external-content.duckduckgo.com/iu/?u=https%3A%2F%2Ftse1.mm.bing.net%2Fth%3Fid%3DOIP.ixpmln2hqkGMPpnBRYRQRAHaE9%26pid%3DApi&f=1",
        "lijfspreuk": "mijn lijfspreuk is mijn lijfgeur",
        "portfolio": {
            "GitHub gebruikersnaam": "drdynscript",
            "LinkedIn gebruikersnaam": "linked-cagravci"
        },
        "isStudentboolean": true,
        "geboortedatum":731363400000
    },
    "person5": {
        "voornaam": "Cagri",
        "familienaam": "Avci",
        "email": "cagravci@student.arteveldehs.be",
        "thumbnail": "https://external-content.duckduckgo.com/iu/?u=https%3A%2F%2Ftse1.mm.bing.net%2Fth%3Fid%3DOIP.ixpmln2hqkGMPpnBRYRQRAHaE9%26pid%3DApi&f=1",
        "lijfspreuk": "mijn lijfspreuk is mijn lijfgeur",
        "portfolio": {
            "GitHub gebruikersnaam": "drdynscript",
            "LinkedIn gebruikersnaam": "linked-cagravci"
        },
        "isStudentboolean": true,
        "geboortedatum":731363400000
    },
    "person6": {
        "voornaam": "Cagri",
        "familienaam": "Avci",
        "email": "cagravci@student.arteveldehs.be",
        "thumbnail": "https://external-content.duckduckgo.com/iu/?u=https%3A%2F%2Ftse1.mm.bing.net%2Fth%3Fid%3DOIP.ixpmln2hqkGMPpnBRYRQRAHaE9%26pid%3DApi&f=1",
        "lijfspreuk": "mijn lijfspreuk is mijn lijfgeur",
        "portfolio": {
            "GitHub gebruikersnaam": "drdynscript",
            "LinkedIn gebruikersnaam": "linked-cagravci"
        },
        "isStudentboolean": true,
        "geboortedatum":731363400000
    },
    "person7": {
        "voornaam": "Cagri",
        "familienaam": "Avci",
        "email": "cagravci@student.arteveldehs.be",
        "thumbnail": "https://external-content.duckduckgo.com/iu/?u=https%3A%2F%2Ftse1.mm.bing.net%2Fth%3Fid%3DOIP.ixpmln2hqkGMPpnBRYRQRAHaE9%26pid%3DApi&f=1",
        "lijfspreuk": "mijn lijfspreuk is mijn lijfgeur",
        "portfolio": {
            "GitHub gebruikersnaam": "drdynscript",
            "LinkedIn gebruikersnaam": "linked-cagravci"
        },
        "isStudentboolean": true,
        "geboortedatum":731363400000
    },
    "person8": {
        "voornaam": "Cagri",
        "familienaam": "Avci",
        "email": "cagravci@student.arteveldehs.be",
        "thumbnail": "https://external-content.duckduckgo.com/iu/?u=https%3A%2F%2Ftse1.mm.bing.net%2Fth%3Fid%3DOIP.ixpmln2hqkGMPpnBRYRQRAHaE9%26pid%3DApi&f=1",
        "lijfspreuk": "mijn lijfspreuk is mijn lijfgeur",
        "portfolio": {
            "GitHub gebruikersnaam": "drdynscript",
            "LinkedIn gebruikersnaam": "linked-cagravci"
        },
        "isStudentboolean": true,
        "geboortedatum":731363400000
    }
}